README.rst
setup.py
BioUtil/__init__.py
BioUtil/bgzip.py
BioUtil/cached_fasta.py
BioUtil/decorator.py
BioUtil/fastq.py
BioUtil/log.py
BioUtil/readfq.py
BioUtil/tsv.py
BioUtil/vcf.py
BioUtil/xz.py
BioUtil.egg-info/PKG-INFO
BioUtil.egg-info/SOURCES.txt
BioUtil.egg-info/dependency_links.txt
BioUtil.egg-info/requires.txt
BioUtil.egg-info/top_level.txt