Metadata-Version: 1.1
Name: BioUtil
Version: 0.4.0
Summary: Bioinfomatics File access tools
Home-page: https://github.com/sein-tao/pyBioUtil
Author: Yu XU
Author-email: xuyu@genomics.cn
License: GPLv2
Keywords: bioinfomatics sequencing fileIO
Platform: UNKNOWN
Classifier: Development Status :: 4 - Beta
Classifier: Intended Audience :: Developers
Classifier: Intended Audience :: Science/Research
Classifier: Topic :: Scientific/Engineering :: Bio-Informatics
Classifier: License :: OSI Approved :: GNU General Public License v2 or later (GPLv2+)
Classifier: Programming Language :: Python :: 3
Classifier: Programming Language :: Python :: 3.4
Classifier: Programming Language :: Python :: 3.5
Classifier: Programming Language :: Python :: 3.6
Classifier: Programming Language :: Python :: 3.7
